{
	"filas": 
	[
		{
			"fila":0,
			"datos":
			[
				{"columna":"0","tile":"1"},
				{"columna":"1","tile":"1"},
				{"columna":"2","tile":"1"},
				{"columna":"3","tile":"1"},
				{"columna":"4","tile":"1"},
				{"columna":"5","tile":"1"},
				{"columna":"6","tile":"1"},
				{"columna":"7","tile":"1"},
				{"columna":"8","tile":"C"},
				{"columna":"9","tile":"C"},
				{"columna":"10","tile":"1"},
				{"columna":"11","tile":"1"},
				{"columna":"12","tile":"1"},
				{"columna":"13","tile":"1"},
				{"columna":"14","tile":"1"},
				{"columna":"15","tile":"1"},
				{"columna":"16","tile":"1"},
				{"columna":"17","tile":"1"}

			]
		},
		{
			"fila":1,
			"datos":
			[
				{"columna":"0","tile":"1"},
				{"columna":"1","tile":"0"},
				{"columna":"2","tile":"0"},
				{"columna":"3","tile":"0"},
				{"columna":"4","tile":"0"},
				{"columna":"5","tile":"0"},
				{"columna":"6","tile":"0"},
				{"columna":"7","tile":"0"},
				{"columna":"8","tile":"0"},
				{"columna":"9","tile":"0"},
				{"columna":"10","tile":"0"},
				{"columna":"11","tile":"0"},
				{"columna":"12","tile":"0"},
				{"columna":"13","tile":"1"},
				{"columna":"14","tile":"0"},
				{"columna":"15","tile":"0"},
				{"columna":"16","tile":"0"},
				{"columna":"17","tile":"1"}

			]
		},
		{
			"fila":2,
			"datos":
			[
				{"columna":"0","tile":"1"},
				{"columna":"1","tile":"0"},
				{"columna":"2","tile":"0"},
				{"columna":"3","tile":"1"},
				{"columna":"4","tile":"0"},
				{"columna":"5","tile":"0"},
				{"columna":"6","tile":"0"},
				{"columna":"7","tile":"4"},
				{"columna":"8","tile":"3"},
				{"columna":"9","tile":"3"},
				{"columna":"10","tile":"5"},
				{"columna":"11","tile":"0"},
				{"columna":"12","tile":"0"},
				{"columna":"13","tile":"7"},
				{"columna":"14","tile":"5"},
				{"columna":"15","tile":"0"},
				{"columna":"16","tile":"0"},
				{"columna":"17","tile":"1"}

			]
		},
		{
			"fila":3,
			"datos":
			[
				{"columna":"0","tile":"1"},
				{"columna":"1","tile":"0"},
				{"columna":"2","tile":"1"},
				{"columna":"3","tile":"6"},
				{"columna":"4","tile":"0"},
				{"columna":"5","tile":"0"},
				{"columna":"6","tile":"1"},
				{"columna":"7","tile":"6"},
				{"columna":"8","tile":"0"},
				{"columna":"9","tile":"0"},
				{"columna":"10","tile":"7"},
				{"columna":"11","tile":"1"},
				{"columna":"12","tile":"0"},
				{"columna":"13","tile":"0"},
				{"columna":"14","tile":"2"},
				{"columna":"15","tile":"0"},
				{"columna":"16","tile":"0"},
				{"columna":"17","tile":"1"}

			]
		},
		{
			"fila":4,
			"datos":
			[
				{"columna":"0","tile":"1"},
				{"columna":"1","tile":"0"},
				{"columna":"2","tile":"0"},
				{"columna":"3","tile":"4"},
				{"columna":"4","tile":"1"},
				{"columna":"5","tile":"0"},
				{"columna":"6","tile":"0"},
				{"columna":"7","tile":"0"},
				{"columna":"8","tile":"0"},
				{"columna":"9","tile":"0"},
				{"columna":"10","tile":"0"},
				{"columna":"11","tile":"0"},
				{"columna":"12","tile":"1"},
				{"columna":"13","tile":"3"},
				{"columna":"14","tile":"3"},
				{"columna":"15","tile":"5"},
				{"columna":"16","tile":"0"},
				{"columna":"17","tile":"1"}

			]
		},
		{
			"fila":5,
			"datos":
			[
				{"columna":"0","tile":"1"},
				{"columna":"1","tile":"3"},
				{"columna":"2","tile":"3"},
				{"columna":"3","tile":"6"},
				{"columna":"4","tile":"0"},
				{"columna":"5","tile":"0"},
				{"columna":"6","tile":"0"},
				{"columna":"7","tile":"0"},
				{"columna":"8","tile":"0"},
				{"columna":"9","tile":"0"},
				{"columna":"10","tile":"0"},
				{"columna":"11","tile":"0"},
				{"columna":"12","tile":"0"},
				{"columna":"13","tile":"0"},
				{"columna":"14","tile":"0"},
				{"columna":"15","tile":"1"},
				{"columna":"16","tile":"0"},
				{"columna":"17","tile":"1"}

			]
		},
		{
			"fila":6,
			"datos":
			[
				{"columna":"0","tile":"1"},
				{"columna":"1","tile":"0"},
				{"columna":"2","tile":"0"},
				{"columna":"3","tile":"0"},
				{"columna":"4","tile":"0"},
				{"columna":"5","tile":"0"},
				{"columna":"6","tile":"4"},
				{"columna":"7","tile":"5"},
				{"columna":"8","tile":"0"},
				{"columna":"9","tile":"0"},
				{"columna":"10","tile":"4"},
				{"columna":"11","tile":"5"},
				{"columna":"12","tile":"0"},
				{"columna":"13","tile":"0"},
				{"columna":"14","tile":"0"},
				{"columna":"15","tile":"0"},
				{"columna":"16","tile":"0"},
				{"columna":"17","tile":"1"}

			]
		},
		{
			"fila":7,
			"datos":
			[
				{"columna":"0","tile":"1"},
				{"columna":"1","tile":"0"},
				{"columna":"2","tile":"0"},
				{"columna":"3","tile":"1"},
				{"columna":"4","tile":"0"},
				{"columna":"5","tile":"0"},
				{"columna":"6","tile":"7"},
				{"columna":"7","tile":"6"},
				{"columna":"8","tile":"0"},
				{"columna":"9","tile":"0"},
				{"columna":"10","tile":"7"},
				{"columna":"11","tile":"6"},
				{"columna":"12","tile":"0"},
				{"columna":"13","tile":"0"},
				{"columna":"14","tile":"1"},
				{"columna":"15","tile":"0"},
				{"columna":"16","tile":"0"},
				{"columna":"17","tile":"1"}

			]
		},
		{
			"fila":8,
			"datos":
			[
				{"columna":"0","tile":"C"},
				{"columna":"1","tile":"0"},
				{"columna":"2","tile":"0"},
				{"columna":"3","tile":"2"},
				{"columna":"4","tile":"0"},
				{"columna":"5","tile":"0"},
				{"columna":"6","tile":"0"},
				{"columna":"7","tile":"0"},
				{"columna":"8","tile":"8"},
				{"columna":"9","tile":"9"},
				{"columna":"10","tile":"0"},
				{"columna":"11","tile":"0"},
				{"columna":"12","tile":"0"},
				{"columna":"13","tile":"0"},
				{"columna":"14","tile":"2"},
				{"columna":"15","tile":"0"},
				{"columna":"16","tile":"0"},
				{"columna":"17","tile":"C"}

			]
		},
		{
			"fila":9,
			"datos":
			[
				{"columna":"0","tile":"C"},
				{"columna":"1","tile":"0"},
				{"columna":"2","tile":"0"},
				{"columna":"3","tile":"2"},
				{"columna":"4","tile":"0"},
				{"columna":"5","tile":"0"},
				{"columna":"6","tile":"0"},
				{"columna":"7","tile":"0"},
				{"columna":"8","tile":"A"},
				{"columna":"9","tile":"B"},
				{"columna":"10","tile":"0"},
				{"columna":"11","tile":"0"},
				{"columna":"12","tile":"0"},
				{"columna":"13","tile":"0"},
				{"columna":"14","tile":"2"},
				{"columna":"15","tile":"0"},
				{"columna":"16","tile":"0"},
				{"columna":"17","tile":"C"}

			]
		},
		{
			"fila":10,
			"datos":
			[
				{"columna":"0","tile":"1"},
				{"columna":"1","tile":"0"},
				{"columna":"2","tile":"0"},
				{"columna":"3","tile":"1"},
				{"columna":"4","tile":"0"},
				{"columna":"5","tile":"0"},
				{"columna":"6","tile":"4"},
				{"columna":"7","tile":"5"},
				{"columna":"8","tile":"0"},
				{"columna":"9","tile":"0"},
				{"columna":"10","tile":"4"},
				{"columna":"11","tile":"5"},
				{"columna":"12","tile":"0"},
				{"columna":"13","tile":"0"},
				{"columna":"14","tile":"1"},
				{"columna":"15","tile":"0"},
				{"columna":"16","tile":"0"},
				{"columna":"17","tile":"1"}

			]
		},
		{
			"fila":11,
			"datos":
			[
				{"columna":"0","tile":"1"},
				{"columna":"1","tile":"0"},
				{"columna":"2","tile":"0"},
				{"columna":"3","tile":"0"},
				{"columna":"4","tile":"0"},
				{"columna":"5","tile":"0"},
				{"columna":"6","tile":"7"},
				{"columna":"7","tile":"6"},
				{"columna":"8","tile":"0"},
				{"columna":"9","tile":"0"},
				{"columna":"10","tile":"7"},
				{"columna":"11","tile":"6"},
				{"columna":"12","tile":"0"},
				{"columna":"13","tile":"0"},
				{"columna":"14","tile":"0"},
				{"columna":"15","tile":"0"},
				{"columna":"16","tile":"0"},
				{"columna":"17","tile":"1"}

			]
		},
		{
			"fila":12,
			"datos":
			[
				{"columna":"0","tile":"1"},
				{"columna":"1","tile":"0"},
				{"columna":"2","tile":"1"},
				{"columna":"3","tile":"0"},
				{"columna":"4","tile":"0"},
				{"columna":"5","tile":"0"},
				{"columna":"6","tile":"0"},
				{"columna":"7","tile":"0"},
				{"columna":"8","tile":"0"},
				{"columna":"9","tile":"0"},
				{"columna":"10","tile":"0"},
				{"columna":"11","tile":"0"},
				{"columna":"12","tile":"0"},
				{"columna":"13","tile":"0"},
				{"columna":"14","tile":"4"},
				{"columna":"15","tile":"3"},
				{"columna":"16","tile":"3"},
				{"columna":"17","tile":"1"}

			]
		},
		{
			"fila":13,
			"datos":
			[
				{"columna":"0","tile":"1"},
				{"columna":"1","tile":"0"},
				{"columna":"2","tile":"0"},
				{"columna":"3","tile":"0"},
				{"columna":"4","tile":"0"},
				{"columna":"5","tile":"0"},
				{"columna":"6","tile":"0"},
				{"columna":"7","tile":"2"},
				{"columna":"8","tile":"0"},
				{"columna":"9","tile":"0"},
				{"columna":"10","tile":"0"},
				{"columna":"11","tile":"0"},
				{"columna":"12","tile":"2"},
				{"columna":"13","tile":"0"},
				{"columna":"14","tile":"4"},
				{"columna":"15","tile":"1"},
				{"columna":"16","tile":"0"},
				{"columna":"17","tile":"1"}

			]
		},
		{
			"fila":14,
			"datos":
			[
				{"columna":"0","tile":"1"},
				{"columna":"1","tile":"0"},
				{"columna":"2","tile":"0"},
				{"columna":"3","tile":"4"},
				{"columna":"4","tile":"3"},
				{"columna":"5","tile":"3"},
				{"columna":"6","tile":"3"},
				{"columna":"7","tile":"6"},
				{"columna":"8","tile":"0"},
				{"columna":"9","tile":"0"},
				{"columna":"10","tile":"0"},
				{"columna":"11","tile":"0"},
				{"columna":"12","tile":"7"},
				{"columna":"13","tile":"3"},
				{"columna":"14","tile":"6"},
				{"columna":"15","tile":"0"},
				{"columna":"16","tile":"0"},
				{"columna":"17","tile":"1"}

			]
		},
		{
			"fila":15,
			"datos":
			[
				{"columna":"0","tile":"1"},
				{"columna":"1","tile":"0"},
				{"columna":"2","tile":"1"},
				{"columna":"3","tile":"6"},
				{"columna":"4","tile":"0"},
				{"columna":"5","tile":"0"},
				{"columna":"6","tile":"4"},
				{"columna":"7","tile":"5"},
				{"columna":"8","tile":"0"},
				{"columna":"9","tile":"0"},
				{"columna":"10","tile":"0"},
				{"columna":"11","tile":"1"},
				{"columna":"12","tile":"3"},
				{"columna":"13","tile":"3"},
				{"columna":"14","tile":"3"},
				{"columna":"15","tile":"1"},
				{"columna":"16","tile":"0"},
				{"columna":"17","tile":"1"}

			]
		},
		{
			"fila":16,
			"datos":
			[
				{"columna":"0","tile":"1"},
				{"columna":"1","tile":"0"},
				{"columna":"2","tile":"0"},
				{"columna":"3","tile":"0"},
				{"columna":"4","tile":"0"},
				{"columna":"5","tile":"0"},
				{"columna":"6","tile":"2"},
				{"columna":"7","tile":"2"},
				{"columna":"8","tile":"0"},
				{"columna":"9","tile":"0"},
				{"columna":"10","tile":"0"},
				{"columna":"11","tile":"0"},
				{"columna":"12","tile":"0"},
				{"columna":"13","tile":"0"},
				{"columna":"14","tile":"0"},
				{"columna":"15","tile":"0"},
				{"columna":"16","tile":"0"},
				{"columna":"17","tile":"1"}

			]
		},
		{
			"fila":17,
			"datos":
			[
				{"columna":"0","tile":"1"},
				{"columna":"1","tile":"1"},
				{"columna":"2","tile":"1"},
				{"columna":"3","tile":"1"},
				{"columna":"4","tile":"1"},
				{"columna":"5","tile":"1"},
				{"columna":"6","tile":"1"},
				{"columna":"7","tile":"1"},
				{"columna":"8","tile":"C"},
				{"columna":"9","tile":"C"},
				{"columna":"10","tile":"1"},
				{"columna":"11","tile":"1"},
				{"columna":"12","tile":"1"},
				{"columna":"13","tile":"1"},
				{"columna":"14","tile":"1"},
				{"columna":"15","tile":"1"},
				{"columna":"16","tile":"1"},
				{"columna":"17","tile":"1"}

			]
		}
	],
	"jugador": 
	[
		{
			"posx":9,
			"posy":6
		},
		{
			"posx":8,
			"posy":11
		}
	]
}